clmutils/__init__.py
clmutils/append_content.py
clmutils/check_running.py
clmutils/chmod600.py
clmutils/config.py
clmutils/create_file.py
clmutils/gen_keypair.py
clmutils/run_cmd.py
clmutils/run_cmd1.py
clmutils/setup_git.py
clmutils/setup_ssh_tunnel.py
clmutils-0.1.5.dist-info/WHEEL
clmutils-0.1.5.dist-info/METADATA
clmutils-0.1.5.dist-info/RECORD
