Metadata-Version: 2.1
Name: clmutils
Version: 0.1.5
Summary: colab miscellaneous utils
Home-page: https://github.com/ffreemt/colab-misc-utils
Author: ffreemt
Requires-Python: >=3.6.1,<4.0.0
Classifier: Programming Language :: Python :: 3
Classifier: Programming Language :: Python :: 3.7
Classifier: Programming Language :: Python :: 3.8
Requires-Dist: chardet (>=4.0.0,<5.0.0)
Requires-Dist: logzero (>=1.6.3,<2.0.0)
Requires-Dist: psutil (>=5.8.0,<6.0.0)
Requires-Dist: pydantic[dotenv] (>=1.7.3,<2.0.0)
Project-URL: Bug Tracker, https://github.com/ffreemt/colab-misc-utils/issues
Project-URL: Repository, https://github.com/ffreemt/colab-misc-utils
